pyredisgears/__init__.py
pyredisgears/redisgears_builder.py
pyredisgears-2.0.1.dist-info/LICENSE
pyredisgears-2.0.1.dist-info/METADATA
pyredisgears-2.0.1.dist-info/WHEEL
pyredisgears-2.0.1.dist-info/RECORD
