Metadata-Version: 2.1
Name: pyredisgears
Version: 2.0.1
Summary: RedisGears Python Client
License: BSD-3-Clause
Keywords: Redis JSON Extension
Author: Redis
Author-email: oss@redis.com
Requires-Python: >=3.9,<3.12
Classifier: Development Status :: 5 - Production/Stable
Classifier: Intended Audience :: Developers
Classifier: License :: OSI Approved :: BSD License
Classifier: Operating System :: OS Independent
Classifier: Programming Language :: Python
Classifier: Programming Language :: Python :: 3
Classifier: Programming Language :: Python :: 3.9
Classifier: Programming Language :: Python :: 3.10
Classifier: Programming Language :: Python :: 3.11
Classifier: Programming Language :: Python :: 3.12
Classifier: Topic :: Database
Requires-Dist: cloudpickle (>=3.1.0,<4.0.0)
Requires-Dist: redis (==4.3.6)
Requires-Dist: rltest (==0.5.8)
Requires-Dist: six (>=1.17.0,<2.0.0)
Project-URL: repository, https://github.com/RedisGears/redisgears-py
Project-URL: url, https://redisgears.io
